sindy_exp/__init__.py
sindy_exp/_data.py
sindy_exp/_diffrax_solver.py
sindy_exp/_dysts_to_sympy.py
sindy_exp/_odes.py
sindy_exp/_plotting.py
sindy_exp/_typing.py
sindy_exp/_utils.py
sindy_exp/addl_attractors.json
sindy_exp/py.typed
sindy_exp-0.2.2.dist-info/licenses/LICENSE
sindy_exp-0.2.2.dist-info/METADATA
sindy_exp-0.2.2.dist-info/WHEEL
sindy_exp-0.2.2.dist-info/top_level.txt
sindy_exp-0.2.2.dist-info/RECORD
