Metadata-Version: 2.4
Name: sindy-exp
Version: 0.2.2
Summary: A basic library for constructing dynamics experiments
Author-email: Jake Stevens-Haas <jacob.stevens.haas@gmail.com>
License: MIT License
Project-URL: homepage, https://github.com/Jake-Stevens-Haas/gen-experiments
Keywords: Machine Learning,Science,Mathematics,Experiments
Classifier: Development Status :: 4 - Beta
Classifier: Programming Language :: Python
Classifier: Framework :: Jupyter
Classifier: Intended Audience :: Science/Research
Classifier: License :: OSI Approved :: MIT License
Classifier: Natural Language :: English
Classifier: Operating System :: POSIX :: Linux
Requires-Python: >=3.10
License-File: LICENSE
Requires-Dist: matplotlib
Requires-Dist: numpy>=2.0.0
Requires-Dist: seaborn
Requires-Dist: scipy
Requires-Dist: sympy
Requires-Dist: dysts
Provides-Extra: jax
Requires-Dist: jax[cuda12]; extra == "jax"
Requires-Dist: diffrax; extra == "jax"
Requires-Dist: sympy2jax; extra == "jax"
Requires-Dist: typing_extensions; extra == "jax"
Provides-Extra: dev
Requires-Dist: ipykernel; extra == "dev"
Requires-Dist: mypy; extra == "dev"
Requires-Dist: pytest>=6.0.0; extra == "dev"
Requires-Dist: pytest-cov; extra == "dev"
Requires-Dist: flake8; extra == "dev"
Requires-Dist: flake8-comprehensions>=3.1.0; extra == "dev"
Requires-Dist: black; extra == "dev"
Requires-Dist: coverage; extra == "dev"
Requires-Dist: isort; extra == "dev"
Requires-Dist: pre-commit; extra == "dev"
Requires-Dist: codecov; extra == "dev"
Requires-Dist: tomli; extra == "dev"
Requires-Dist: pysindy>=2.1.0; extra == "dev"
Dynamic: license-file
